WuyunZhishikuDierBufenFix1/README.md
WuyunZhishikuDierBufenFix1/__init__.py
WuyunZhishikuDierBufenFix1/__main__.py
WuyunZhishikuDierBufenFix1/file.epub
WuyunZhishikuDierBufenFix1/index.html
WuyunZhishikuDierBufenFix1/css/__init__.py
WuyunZhishikuDierBufenFix1/css/annotations.css
WuyunZhishikuDierBufenFix1/css/main.css
WuyunZhishikuDierBufenFix1/css/normalize.css
WuyunZhishikuDierBufenFix1/css/popup.css
WuyunZhishikuDierBufenFix1/font/__init__.py
WuyunZhishikuDierBufenFix1/font/fontello.eot
WuyunZhishikuDierBufenFix1/font/fontello.svg
WuyunZhishikuDierBufenFix1/font/fontello.ttf
WuyunZhishikuDierBufenFix1/font/fontello.woff
WuyunZhishikuDierBufenFix1/img/__init__.py
WuyunZhishikuDierBufenFix1/img/annotator-glyph-sprite.png
WuyunZhishikuDierBufenFix1/img/annotator-icon-sprite.png
WuyunZhishikuDierBufenFix1/img/apple-touch-icon.png
WuyunZhishikuDierBufenFix1/img/cancelfullscreen.png
WuyunZhishikuDierBufenFix1/img/close.png
WuyunZhishikuDierBufenFix1/img/fullscreen.png
WuyunZhishikuDierBufenFix1/img/loader.gif
WuyunZhishikuDierBufenFix1/img/menu-icon.png
WuyunZhishikuDierBufenFix1/img/save.png
WuyunZhishikuDierBufenFix1/img/saved.png
WuyunZhishikuDierBufenFix1/img/settings-s.png
WuyunZhishikuDierBufenFix1/img/settings.png
WuyunZhishikuDierBufenFix1/img/star.png
WuyunZhishikuDierBufenFix1/js/__init__.py
WuyunZhishikuDierBufenFix1/js/epub.js
WuyunZhishikuDierBufenFix1/js/epub.min.js
WuyunZhishikuDierBufenFix1/js/epub.min.map
WuyunZhishikuDierBufenFix1/js/hooks.min.js
WuyunZhishikuDierBufenFix1/js/hooks.min.map
WuyunZhishikuDierBufenFix1/js/reader.js
WuyunZhishikuDierBufenFix1/js/reader.js.map
WuyunZhishikuDierBufenFix1/js/reader.min.js
WuyunZhishikuDierBufenFix1/js/reader.min.map
WuyunZhishikuDierBufenFix1/js/hooks/__init__.py
WuyunZhishikuDierBufenFix1/js/hooks/extensions/__init__.py
WuyunZhishikuDierBufenFix1/js/hooks/extensions/highlight.js
WuyunZhishikuDierBufenFix1/js/libs/__init__.py
WuyunZhishikuDierBufenFix1/js/libs/jquery.min.js
wuyun_zhishiku_dier_bufen_fix1-2025.3.24.0.dist-info/METADATA
wuyun_zhishiku_dier_bufen_fix1-2025.3.24.0.dist-info/WHEEL
wuyun_zhishiku_dier_bufen_fix1-2025.3.24.0.dist-info/entry_points.txt
wuyun_zhishiku_dier_bufen_fix1-2025.3.24.0.dist-info/top_level.txt
wuyun_zhishiku_dier_bufen_fix1-2025.3.24.0.dist-info/RECORD
